pypicloud_client/__init__.py
pypicloud_client/client.py
pypicloud_client/http.py
pypicloud_client-6.dist-info/DESCRIPTION.rst
pypicloud_client-6.dist-info/METADATA
pypicloud_client-6.dist-info/RECORD
pypicloud_client-6.dist-info/WHEEL
pypicloud_client-6.dist-info/metadata.json
pypicloud_client-6.dist-info/top_level.txt
