Metadata-Version: 2.0
Name: pypicloud-client
Version: 6
Summary: Provide a client for pypicloud
Home-page: https://github.com/tinyclues/pypicloud_client
Author: Damien Goldenberg
Author-email: damien.goldenberg@tinyclues.com
License: UNKNOWN
Keywords: pypicloud,client
Platform: UNKNOWN
Classifier: Development Status :: 2 - Pre-Alpha
Classifier: Natural Language :: English
Classifier: Programming Language :: Python :: 2.7
Requires-Dist: furl (==0.4.95)
Requires-Dist: requests (>=2.7.0)
